excel_csv_decimal_converter_nikrapy/__init__.py
excel_csv_decimal_converter_nikrapy/csvconvertergui.py
excel_csv_decimal_converter_nikrapy/csvdecimalconverter.py
excelcsvformatconverter-0.1.0.dist-info/METADATA
excelcsvformatconverter-0.1.0.dist-info/WHEEL
excelcsvformatconverter-0.1.0.dist-info/entry_points.txt
excelcsvformatconverter-0.1.0.dist-info/top_level.txt
excelcsvformatconverter-0.1.0.dist-info/RECORD
