Metadata-Version: 2.1
Name: excelcsvformatconverter
Version: 0.1.0
Summary: Converter to convert a Picoscope generated csv file to a excel compatible one.
Author-email: Nils Krause <github@nils.online>
License: MIT
Project-URL: Homepage, https://github.com/krauni/excelcsvconverter
Requires-Python: >=3.9
